odoo/addons/product_end_of_life/README.rst
odoo/addons/product_end_of_life/__init__.py
odoo/addons/product_end_of_life/__manifest__.py
odoo/addons/product_end_of_life/data/ir_cron.xml
odoo/addons/product_end_of_life/data/mail_channel_data.xml
odoo/addons/product_end_of_life/models/__init__.py
odoo/addons/product_end_of_life/models/product.py
odoo/addons/product_end_of_life/models/res_config_settings.py
odoo/addons/product_end_of_life/static/description/icon.png
odoo/addons/product_end_of_life/tests/__init__.py
odoo/addons/product_end_of_life/tests/test_product_eol.py
odoo/addons/product_end_of_life/views/mail_templates.xml
odoo/addons/product_end_of_life/views/product_view.xml
odoo/addons/product_end_of_life/views/purchase_view.xml
odoo/addons/product_end_of_life/views/res_config_settings_view.xml
odoo11_addon_product_end_of_life-11.0.1.0.0.dist-info/DESCRIPTION.rst
odoo11_addon_product_end_of_life-11.0.1.0.0.dist-info/METADATA
odoo11_addon_product_end_of_life-11.0.1.0.0.dist-info/RECORD
odoo11_addon_product_end_of_life-11.0.1.0.0.dist-info/WHEEL
odoo11_addon_product_end_of_life-11.0.1.0.0.dist-info/metadata.json
odoo11_addon_product_end_of_life-11.0.1.0.0.dist-info/top_level.txt
